{
  "extends": [
    "tslint:recommended"
  ],
  "rules": {
    "max-classes-per-file": false,
    "ban-types": false,
    "unified-signatures": false,
    "object-literal-sort-keys": true,
    "member-ordering": [
      true,
      {
        "order": [
          "public-constructor",
          "protected-constructor",
          "private-constructor",
          "public-static-field",
          "protected-static-field",
          "private-static-field",
          "public-static-method",
          "protected-static-method",
          "private-static-method",
          "public-instance-field",
          "public-instance-method",
          "protected-instance-field",
          "protected-instance-method",
          "private-instance-field",
          "private-instance-method"
        ],
        "alphabetize": true
      }
    ]
  }
}
